classmods/__init__.py
classmods/__version__.py
classmods/_decorators.py
classmods/_descriptors.py
classmods/_env_mod.py
classmods/_method_monitor.py
classmods-1.2.2.dist-info/licenses/LICENSE
classmods-1.2.2.dist-info/METADATA
classmods-1.2.2.dist-info/WHEEL
classmods-1.2.2.dist-info/top_level.txt
classmods-1.2.2.dist-info/RECORD
