Metadata-Version: 2.4
Name: classmods
Version: 1.2.2
Summary: Simple mods for python classes.
Home-page: https://github.com/hmohammad2520-org/classmods/
Author: hmohammad2520-org
Author-email: hmohammad2520-org <hmohammad2520@gmail.com>
License: MIT License
Project-URL: Homepage, https://github.com/hmohammad2520-org/classmods
Project-URL: BugTracker, https://github.com/hmohammad2520-org/classmods/issues
Keywords: python,class,mods,modification,descriptors,methods,methodmod,methodobserve
Classifier: Programming Language :: Python :: 3
Classifier: License :: OSI Approved :: MIT License
Classifier: Operating System :: OS Independent
Requires-Python: >=3.12
License-File: LICENSE
Dynamic: author
Dynamic: home-page
Dynamic: license-file
